cli_todo_jd/__init__.py
cli_todo_jd/cli_entry.py
cli_todo_jd/main.py
cli_todo_jd/storage/__init__.py
cli_todo_jd/storage/migrate.py
cli_todo_jd/storage/schema.py
cli_todo_jd-0.2.1.dist-info/METADATA
cli_todo_jd-0.2.1.dist-info/WHEEL
cli_todo_jd-0.2.1.dist-info/entry_points.txt
cli_todo_jd-0.2.1.dist-info/top_level.txt
cli_todo_jd-0.2.1.dist-info/RECORD
