Metadata-Version: 2.4
Name: cli-todo-jd
Version: 0.2.1
Summary: Add your description here
Requires-Python: >=3.10
Requires-Dist: questionary>=2.1.1
Requires-Dist: rich>=14.2.0
Requires-Dist: typer>=0.21.1
Provides-Extra: dev
Requires-Dist: pre-commit; extra == "dev"
Requires-Dist: pytest; extra == "dev"
Requires-Dist: bump-my-version; extra == "dev"
